Metadata-Version: 2.1
Name: nextai-vllm
Version: 0.0.7
Summary: A high-throughput and memory-efficient inference and serving engine for LLMs
Home-page: https://github.com/vllm-project/vllm
Author: NextAI Team
License: Apache 2.0
Project-URL: Homepage, https://github.com/vllm-project/vllm
Project-URL: Documentation, https://vllm.readthedocs.io/en/latest/
Classifier: Programming Language :: Python :: 3.8
Classifier: Programming Language :: Python :: 3.9
Classifier: Programming Language :: Python :: 3.10
Classifier: Programming Language :: Python :: 3.11
Classifier: License :: OSI Approved :: Apache Software License
Classifier: Topic :: Scientific/Engineering :: Artificial Intelligence
Requires-Python: >=3.8
License-File: LICENSE
Requires-Dist: cmake (>=3.21)
Requires-Dist: ninja
Requires-Dist: psutil
Requires-Dist: sentencepiece
Requires-Dist: numpy
Requires-Dist: requests
Requires-Dist: py-cpuinfo
Requires-Dist: transformers (>=4.39.1)
Requires-Dist: fastapi
Requires-Dist: uvicorn[standard]
Requires-Dist: pydantic (>=2.0)
Requires-Dist: prometheus-client (>=0.18.0)
Requires-Dist: tiktoken (==0.6.0)
Requires-Dist: outlines (==0.0.34)
Requires-Dist: ray (>=2.9)
Requires-Dist: pynvml (==11.5.0)
Requires-Dist: vllm-nccl-cu12 (<2.19,>=2.18)
Requires-Dist: torch (==2.1.2)
Requires-Dist: xformers (==0.0.23.post1)
Requires-Dist: triton (>=2.1.0)
